erbsland_maze/VERSION.txt
erbsland_maze/__init__.py
erbsland_maze/about.py
erbsland_maze/blank_modifier.py
erbsland_maze/closing.py
erbsland_maze/closing_modifier.py
erbsland_maze/closing_type.py
erbsland_maze/color.py
erbsland_maze/connection_side.py
erbsland_maze/corner.py
erbsland_maze/direction.py
erbsland_maze/error_mark.py
erbsland_maze/frame_modifier.py
erbsland_maze/generator.py
erbsland_maze/generator_error.py
erbsland_maze/generator_setup.py
erbsland_maze/generator_stack.py
erbsland_maze/layout.py
erbsland_maze/line.py
erbsland_maze/location_grid.py
erbsland_maze/merge_modifier.py
erbsland_maze/modifier.py
erbsland_maze/modifier_error.py
erbsland_maze/modifier_type.py
erbsland_maze/modifiers.py
erbsland_maze/parity.py
erbsland_maze/path_end.py
erbsland_maze/path_groups.py
erbsland_maze/path_join_info.py
erbsland_maze/path_pair.py
erbsland_maze/placement.py
erbsland_maze/point.py
erbsland_maze/poly_line.py
erbsland_maze/rectangle.py
erbsland_maze/room.py
erbsland_maze/room_connection.py
erbsland_maze/room_grid.py
erbsland_maze/room_insets.py
erbsland_maze/room_location.py
erbsland_maze/room_offset.py
erbsland_maze/room_size.py
erbsland_maze/room_type.py
erbsland_maze/size.py
erbsland_maze/svg_fill_mode.py
erbsland_maze/svg_layout.py
erbsland_maze/svg_setup.py
erbsland_maze/svg_unit.py
erbsland_maze/svg_zero_point.py
erbsland_maze/types.py
erbsland_maze/wall.py
erbsland_maze/wall_points.py
erbsland_maze-1.3.2.dist-info/licenses/LICENSE
erbsland_maze-1.3.2.dist-info/licenses/LICENSE.md
erbsland_maze-1.3.2.dist-info/METADATA
erbsland_maze-1.3.2.dist-info/WHEEL
erbsland_maze-1.3.2.dist-info/top_level.txt
erbsland_maze-1.3.2.dist-info/RECORD
