Metadata-Version: 2.4
Name: erbsland_maze
Version: 1.3.2
Summary: A fast, modular and customizable generator for rectangular mazes.
Author-email: Erbsland DEV <info@erbsland.dev>
License: GPL-3.0-or-later
Project-URL: Documentation, https://erbsland-dev.github.io/erbsland-maze/
Project-URL: Source, https://github.com/erbsland-dev/erbsland-maze
Project-URL: Issues, https://github.com/erbsland-dev/erbsland-maze/issues
Classifier: Development Status :: 5 - Production/Stable
Classifier: Environment :: Console
Classifier: Intended Audience :: Developers
Classifier: Intended Audience :: End Users/Desktop
Classifier: Operating System :: OS Independent
Classifier: Programming Language :: Python :: 3
Classifier: Programming Language :: Python :: 3.12
Classifier: Topic :: Games/Entertainment :: Puzzle Games
Classifier: Topic :: Multimedia :: Graphics
Classifier: Topic :: Scientific/Engineering :: Visualization
Requires-Python: >=3.12
License-File: LICENSE
License-File: LICENSE.md
Requires-Dist: pycairo>=1.26.0
Dynamic: license-file
